ommlx/.manifests.json
ommlx/__about__.py
ommlx/__init__.py
ommlx/huggingface.py
ommlx/backends/__init__.py
ommlx/backends/llamacpp/__init__.py
ommlx/backends/llamacpp/buildwheel.py
ommlx/backends/llamacpp/logging.py
ommlx/backends/mlx/__init__.py
ommlx/backends/mlx/__main__.py
ommlx/backends/mlx/caching.py
ommlx/backends/mlx/cli.py
ommlx/backends/mlx/generation.py
ommlx/backends/mlx/limits.py
ommlx/backends/mlx/loading.py
ommlx/backends/mlx/tokenization/LICENSE
ommlx/backends/mlx/tokenization/__init__.py
ommlx/backends/mlx/tokenization/loading.py
ommlx/backends/mlx/tokenization/tokenization.py
ommlx/backends/mlx/tokenization/types.py
ommlx/backends/mlx/tokenization/detokenization/__init__.py
ommlx/backends/mlx/tokenization/detokenization/base.py
ommlx/backends/mlx/tokenization/detokenization/bpe.py
ommlx/backends/mlx/tokenization/detokenization/naive.py
ommlx/backends/mlx/tokenization/detokenization/spm.py
ommlx/backends/sentencepiece/__init__.py
ommlx/backends/sentencepiece/tokens.py
ommlx/backends/tiktoken/__init__.py
ommlx/backends/tinygrad/__init__.py
ommlx/backends/tinygrad/tinygrad.py
ommlx/backends/tinygrad/models/LICENSE
ommlx/backends/tinygrad/models/__init__.py
ommlx/backends/tinygrad/models/llama3/__init__.py
ommlx/backends/tinygrad/models/llama3/__main__.py
ommlx/backends/tinygrad/models/llama3/attention.py
ommlx/backends/tinygrad/models/llama3/fetch.py
ommlx/backends/tinygrad/models/llama3/llm.py
ommlx/backends/tinygrad/models/llama3/loading.py
ommlx/backends/tinygrad/models/llama3/quantization.py
ommlx/backends/tinygrad/models/llama3/repl.py
ommlx/backends/tinygrad/models/llama3/sampling.py
ommlx/backends/tinygrad/models/llama3/tokenization.py
ommlx/backends/tinygrad/models/llama3/transformer.py
ommlx/backends/tinygrad/models/sdxl/__init__.py
ommlx/backends/tinygrad/models/sdxl/__main__.py
ommlx/backends/tinygrad/models/sdxl/cli.py
ommlx/backends/tinygrad/models/sdxl/clip.py
ommlx/backends/tinygrad/models/sdxl/sdxl.py
ommlx-0.0.0.dev323.dist-info/licenses/LICENSE
ommlx-0.0.0.dev323.dist-info/METADATA
ommlx-0.0.0.dev323.dist-info/WHEEL
ommlx-0.0.0.dev323.dist-info/entry_points.txt
ommlx-0.0.0.dev323.dist-info/top_level.txt
ommlx-0.0.0.dev323.dist-info/RECORD
