Metadata-Version: 2.4
Name: ommlx
Version: 0.0.0.dev323
Summary: ommlx
Author: wrmsr
License: BSD-3-Clause
Project-URL: source, https://github.com/wrmsr/omlish
Classifier: License :: OSI Approved :: BSD License
Classifier: Development Status :: 2 - Pre-Alpha
Classifier: Intended Audience :: Developers
Classifier: Operating System :: OS Independent
Classifier: Operating System :: POSIX
Requires-Python: >=3.12
License-File: LICENSE
Requires-Dist: omdev==0.0.0.dev323
Requires-Dist: omlish==0.0.0.dev323
Provides-Extra: all
Requires-Dist: llama-cpp-python~=0.3; extra == "all"
Requires-Dist: mlx~=0.25; extra == "all"
Requires-Dist: mlx-lm~=0.24; sys_platform == "darwin" and extra == "all"
Requires-Dist: sentencepiece~=0.2; extra == "all"
Requires-Dist: tiktoken~=0.9; extra == "all"
Requires-Dist: tinygrad~=0.10; extra == "all"
Requires-Dist: tokenizers~=0.21; extra == "all"
Requires-Dist: torch~=2.7; extra == "all"
Requires-Dist: transformers~=4.52; extra == "all"
Requires-Dist: sentence-transformers~=4.1; extra == "all"
Requires-Dist: huggingface-hub~=0.32; extra == "all"
Requires-Dist: datasets~=3.6; extra == "all"
Requires-Dist: numpy>=1.26; extra == "all"
Requires-Dist: pytesseract~=0.3; extra == "all"
Requires-Dist: rapidocr-onnxruntime~=1.4; extra == "all"
Requires-Dist: pillow~=11.1; extra == "all"
Requires-Dist: duckduckgo-search~=8.0; extra == "all"
Requires-Dist: mwparserfromhell~=0.6; extra == "all"
Requires-Dist: wikitextparser~=0.56; extra == "all"
Requires-Dist: lxml~=5.3; python_version < "3.13" and extra == "all"
Provides-Extra: backends
Requires-Dist: llama-cpp-python~=0.3; extra == "backends"
Requires-Dist: mlx~=0.25; extra == "backends"
Requires-Dist: mlx-lm~=0.24; sys_platform == "darwin" and extra == "backends"
Requires-Dist: sentencepiece~=0.2; extra == "backends"
Requires-Dist: tiktoken~=0.9; extra == "backends"
Requires-Dist: tinygrad~=0.10; extra == "backends"
Requires-Dist: tokenizers~=0.21; extra == "backends"
Requires-Dist: torch~=2.7; extra == "backends"
Requires-Dist: transformers~=4.52; extra == "backends"
Requires-Dist: sentence-transformers~=4.1; extra == "backends"
Provides-Extra: huggingface
Requires-Dist: huggingface-hub~=0.32; extra == "huggingface"
Requires-Dist: datasets~=3.6; extra == "huggingface"
Provides-Extra: numpy
Requires-Dist: numpy>=1.26; extra == "numpy"
Provides-Extra: ocr
Requires-Dist: pytesseract~=0.3; extra == "ocr"
Requires-Dist: rapidocr-onnxruntime~=1.4; extra == "ocr"
Provides-Extra: pillow
Requires-Dist: pillow~=11.1; extra == "pillow"
Provides-Extra: search
Requires-Dist: duckduckgo-search~=8.0; extra == "search"
Provides-Extra: wiki
Requires-Dist: mwparserfromhell~=0.6; extra == "wiki"
Requires-Dist: wikitextparser~=0.56; extra == "wiki"
Provides-Extra: xml
Requires-Dist: lxml~=5.3; python_version < "3.13" and extra == "xml"
Dynamic: license-file
